{
  "protocol": "ether.fi",
  "period": "2025-01",
  "source": "defillama+coingecko",
  "fetched_at": "2026-02-09T07:05:04.730Z",
  "record_count": 31,
  "records": [
    {
      "date": "2025-01-01",
      "price_usd": null,
      "market_cap_usd": null,
      "daily_fees_usd": 599381,
      "daily_revenue_usd": 119237,
      "daily_holders_revenue_usd": 0,
      "daily_tev_usd": 0,
      "tev_source": "defillama_holdersRevenue"
    },
    {
      "date": "2025-01-02",
      "price_usd": null,
      "market_cap_usd": null,
      "daily_fees_usd": 653288,
      "daily_revenue_usd": 134851,
      "daily_holders_revenue_usd": 0,
      "daily_tev_usd": 0,
      "tev_source": "defillama_holdersRevenue"
    },
    {
      "date": "2025-01-03",
      "price_usd": null,
      "market_cap_usd": null,
      "daily_fees_usd": 689117,
      "daily_revenue_usd": 142183,
      "daily_holders_revenue_usd": 0,
      "daily_tev_usd": 0,
      "tev_source": "defillama_holdersRevenue"
    },
    {
      "date": "2025-01-04",
      "price_usd": null,
      "market_cap_usd": null,
      "daily_fees_usd": 622212,
      "daily_revenue_usd": 131046,
      "daily_holders_revenue_usd": 0,
      "daily_tev_usd": 0,
      "tev_source": "defillama_holdersRevenue"
    },
    {
      "date": "2025-01-05",
      "price_usd": null,
      "market_cap_usd": null,
      "daily_fees_usd": 696421,
      "daily_revenue_usd": 144664,
      "daily_holders_revenue_usd": 0,
      "daily_tev_usd": 0,
      "tev_source": "defillama_holdersRevenue"
    },
    {
      "date": "2025-01-06",
      "price_usd": null,
      "market_cap_usd": null,
      "daily_fees_usd": 636156,
      "daily_revenue_usd": 133887,
      "daily_holders_revenue_usd": 0,
      "daily_tev_usd": 0,
      "tev_source": "defillama_holdersRevenue"
    },
    {
      "date": "2025-01-07",
      "price_usd": null,
      "market_cap_usd": null,
      "daily_fees_usd": 1389640,
      "daily_revenue_usd": 853338,
      "daily_holders_revenue_usd": 0,
      "daily_tev_usd": 0,
      "tev_source": "defillama_holdersRevenue"
    },
    {
      "date": "2025-01-08",
      "price_usd": null,
      "market_cap_usd": null,
      "daily_fees_usd": 650641,
      "daily_revenue_usd": 134458,
      "daily_holders_revenue_usd": 0,
      "daily_tev_usd": 0,
      "tev_source": "defillama_holdersRevenue"
    },
    {
      "date": "2025-01-09",
      "price_usd": null,
      "market_cap_usd": null,
      "daily_fees_usd": 573194,
      "daily_revenue_usd": 119468,
      "daily_holders_revenue_usd": 0,
      "daily_tev_usd": 0,
      "tev_source": "defillama_holdersRevenue"
    },
    {
      "date": "2025-01-10",
      "price_usd": null,
      "market_cap_usd": null,
      "daily_fees_usd": 831518,
      "daily_revenue_usd": 327350,
      "daily_holders_revenue_usd": 0,
      "daily_tev_usd": 0,
      "tev_source": "defillama_holdersRevenue"
    },
    {
      "date": "2025-01-11",
      "price_usd": null,
      "market_cap_usd": null,
      "daily_fees_usd": 467476,
      "daily_revenue_usd": 101014,
      "daily_holders_revenue_usd": 0,
      "daily_tev_usd": 0,
      "tev_source": "defillama_holdersRevenue"
    },
    {
      "date": "2025-01-12",
      "price_usd": null,
      "market_cap_usd": null,
      "daily_fees_usd": 699771,
      "daily_revenue_usd": 143267,
      "daily_holders_revenue_usd": 0,
      "daily_tev_usd": 0,
      "tev_source": "defillama_holdersRevenue"
    },
    {
      "date": "2025-01-13",
      "price_usd": null,
      "market_cap_usd": null,
      "daily_fees_usd": 561695,
      "daily_revenue_usd": 116612,
      "daily_holders_revenue_usd": 0,
      "daily_tev_usd": 0,
      "tev_source": "defillama_holdersRevenue"
    },
    {
      "date": "2025-01-14",
      "price_usd": null,
      "market_cap_usd": null,
      "daily_fees_usd": 592183,
      "daily_revenue_usd": 130325,
      "daily_holders_revenue_usd": 0,
      "daily_tev_usd": 0,
      "tev_source": "defillama_holdersRevenue"
    },
    {
      "date": "2025-01-15",
      "price_usd": null,
      "market_cap_usd": null,
      "daily_fees_usd": 700992,
      "daily_revenue_usd": 660780,
      "daily_holders_revenue_usd": 0,
      "daily_tev_usd": 0,
      "tev_source": "defillama_holdersRevenue"
    },
    {
      "date": "2025-01-16",
      "price_usd": null,
      "market_cap_usd": null,
      "daily_fees_usd": 1203854,
      "daily_revenue_usd": 234847,
      "daily_holders_revenue_usd": 0,
      "daily_tev_usd": 0,
      "tev_source": "defillama_holdersRevenue"
    },
    {
      "date": "2025-01-17",
      "price_usd": null,
      "market_cap_usd": null,
      "daily_fees_usd": 447086,
      "daily_revenue_usd": 158794,
      "daily_holders_revenue_usd": 0,
      "daily_tev_usd": 0,
      "tev_source": "defillama_holdersRevenue"
    },
    {
      "date": "2025-01-18",
      "price_usd": null,
      "market_cap_usd": null,
      "daily_fees_usd": 885359,
      "daily_revenue_usd": 176822,
      "daily_holders_revenue_usd": 0,
      "daily_tev_usd": 0,
      "tev_source": "defillama_holdersRevenue"
    },
    {
      "date": "2025-01-19",
      "price_usd": null,
      "market_cap_usd": null,
      "daily_fees_usd": 565866,
      "daily_revenue_usd": 117870,
      "daily_holders_revenue_usd": 0,
      "daily_tev_usd": 0,
      "tev_source": "defillama_holdersRevenue"
    },
    {
      "date": "2025-01-20",
      "price_usd": null,
      "market_cap_usd": null,
      "daily_fees_usd": 809561,
      "daily_revenue_usd": 161690,
      "daily_holders_revenue_usd": 0,
      "daily_tev_usd": 0,
      "tev_source": "defillama_holdersRevenue"
    },
    {
      "date": "2025-01-21",
      "price_usd": null,
      "market_cap_usd": null,
      "daily_fees_usd": 81422,
      "daily_revenue_usd": 36474,
      "daily_holders_revenue_usd": 0,
      "daily_tev_usd": 0,
      "tev_source": "defillama_holdersRevenue"
    },
    {
      "date": "2025-01-22",
      "price_usd": null,
      "market_cap_usd": null,
      "daily_fees_usd": 1223996,
      "daily_revenue_usd": 238121,
      "daily_holders_revenue_usd": 0,
      "daily_tev_usd": 0,
      "tev_source": "defillama_holdersRevenue"
    },
    {
      "date": "2025-01-23",
      "price_usd": null,
      "market_cap_usd": null,
      "daily_fees_usd": 599345,
      "daily_revenue_usd": 125131,
      "daily_holders_revenue_usd": 0,
      "daily_tev_usd": 0,
      "tev_source": "defillama_holdersRevenue"
    },
    {
      "date": "2025-01-24",
      "price_usd": null,
      "market_cap_usd": null,
      "daily_fees_usd": 806508,
      "daily_revenue_usd": 263985,
      "daily_holders_revenue_usd": 0,
      "daily_tev_usd": 0,
      "tev_source": "defillama_holdersRevenue"
    },
    {
      "date": "2025-01-25",
      "price_usd": null,
      "market_cap_usd": null,
      "daily_fees_usd": 619437,
      "daily_revenue_usd": 128784,
      "daily_holders_revenue_usd": 0,
      "daily_tev_usd": 0,
      "tev_source": "defillama_holdersRevenue"
    },
    {
      "date": "2025-01-26",
      "price_usd": null,
      "market_cap_usd": null,
      "daily_fees_usd": 564219,
      "daily_revenue_usd": 118538,
      "daily_holders_revenue_usd": 0,
      "daily_tev_usd": 0,
      "tev_source": "defillama_holdersRevenue"
    },
    {
      "date": "2025-01-27",
      "price_usd": null,
      "market_cap_usd": null,
      "daily_fees_usd": 463730,
      "daily_revenue_usd": 99936,
      "daily_holders_revenue_usd": 0,
      "daily_tev_usd": 0,
      "tev_source": "defillama_holdersRevenue"
    },
    {
      "date": "2025-01-28",
      "price_usd": null,
      "market_cap_usd": null,
      "daily_fees_usd": 551018,
      "daily_revenue_usd": 121313,
      "daily_holders_revenue_usd": 0,
      "daily_tev_usd": 0,
      "tev_source": "defillama_holdersRevenue"
    },
    {
      "date": "2025-01-29",
      "price_usd": null,
      "market_cap_usd": null,
      "daily_fees_usd": 616718,
      "daily_revenue_usd": 127827,
      "daily_holders_revenue_usd": 0,
      "daily_tev_usd": 0,
      "tev_source": "defillama_holdersRevenue"
    },
    {
      "date": "2025-01-30",
      "price_usd": null,
      "market_cap_usd": null,
      "daily_fees_usd": 620086,
      "daily_revenue_usd": 128952,
      "daily_holders_revenue_usd": 0,
      "daily_tev_usd": 0,
      "tev_source": "defillama_holdersRevenue"
    },
    {
      "date": "2025-01-31",
      "price_usd": null,
      "market_cap_usd": null,
      "daily_fees_usd": 687831,
      "daily_revenue_usd": 141690,
      "daily_holders_revenue_usd": 165000,
      "daily_tev_usd": 165000,
      "tev_source": "defillama_holdersRevenue"
    }
  ]
}