{
  "protocol": "sky",
  "period": "2023-11",
  "source": "defillama+binance",
  "fetched_at": "2026-02-01T16:42:49.403Z",
  "record_count": 30,
  "records": [
    {
      "date": "2023-11-01",
      "price_usd": 1339,
      "market_cap_usd": null,
      "daily_fees_usd": 557759,
      "daily_tev_usd": 337567,
      "tev_ratio_used": 0.7,
      "daily_revenue_usd": 337567,
      "tev_source": "defillama_revenue"
    },
    {
      "date": "2023-11-02",
      "price_usd": 1308,
      "market_cap_usd": null,
      "daily_fees_usd": 569271,
      "daily_tev_usd": 347332,
      "tev_ratio_used": 0.7,
      "daily_revenue_usd": 347332,
      "tev_source": "defillama_revenue"
    },
    {
      "date": "2023-11-03",
      "price_usd": 1338,
      "market_cap_usd": null,
      "daily_fees_usd": 567618,
      "daily_tev_usd": 345847,
      "tev_ratio_used": 0.7,
      "daily_revenue_usd": 345847,
      "tev_source": "defillama_revenue"
    },
    {
      "date": "2023-11-04",
      "price_usd": 1338,
      "market_cap_usd": null,
      "daily_fees_usd": 548737,
      "daily_tev_usd": 325694,
      "tev_ratio_used": 0.7,
      "daily_revenue_usd": 325694,
      "tev_source": "defillama_revenue"
    },
    {
      "date": "2023-11-05",
      "price_usd": 1328,
      "market_cap_usd": null,
      "daily_fees_usd": 549371,
      "daily_tev_usd": 327271,
      "tev_ratio_used": 0.7,
      "daily_revenue_usd": 327271,
      "tev_source": "defillama_revenue"
    },
    {
      "date": "2023-11-06",
      "price_usd": 1335,
      "market_cap_usd": null,
      "daily_fees_usd": 560533,
      "daily_tev_usd": 339190,
      "tev_ratio_used": 0.7,
      "daily_revenue_usd": 339190,
      "tev_source": "defillama_revenue"
    },
    {
      "date": "2023-11-07",
      "price_usd": 1296,
      "market_cap_usd": null,
      "daily_fees_usd": 563578,
      "daily_tev_usd": 340982,
      "tev_ratio_used": 0.7,
      "daily_revenue_usd": 340982,
      "tev_source": "defillama_revenue"
    },
    {
      "date": "2023-11-08",
      "price_usd": 1314,
      "market_cap_usd": null,
      "daily_fees_usd": 561516,
      "daily_tev_usd": 342625,
      "tev_ratio_used": 0.7,
      "daily_revenue_usd": 342625,
      "tev_source": "defillama_revenue"
    },
    {
      "date": "2023-11-09",
      "price_usd": 1376,
      "market_cap_usd": null,
      "daily_fees_usd": 562179,
      "daily_tev_usd": 347854,
      "tev_ratio_used": 0.7,
      "daily_revenue_usd": 347854,
      "tev_source": "defillama_revenue"
    },
    {
      "date": "2023-11-10",
      "price_usd": 1322,
      "market_cap_usd": null,
      "daily_fees_usd": 567156,
      "daily_tev_usd": 355853,
      "tev_ratio_used": 0.7,
      "daily_revenue_usd": 355853,
      "tev_source": "defillama_revenue"
    },
    {
      "date": "2023-11-11",
      "price_usd": 1287,
      "market_cap_usd": null,
      "daily_fees_usd": 557673,
      "daily_tev_usd": 345210,
      "tev_ratio_used": 0.7,
      "daily_revenue_usd": 345210,
      "tev_source": "defillama_revenue"
    },
    {
      "date": "2023-11-12",
      "price_usd": 1290,
      "market_cap_usd": null,
      "daily_fees_usd": 560483,
      "daily_tev_usd": 346544,
      "tev_ratio_used": 0.7,
      "daily_revenue_usd": 346544,
      "tev_source": "defillama_revenue"
    },
    {
      "date": "2023-11-13",
      "price_usd": 1379,
      "market_cap_usd": null,
      "daily_fees_usd": 574173,
      "daily_tev_usd": 361551,
      "tev_ratio_used": 0.7,
      "daily_revenue_usd": 361551,
      "tev_source": "defillama_revenue"
    },
    {
      "date": "2023-11-14",
      "price_usd": 1384,
      "market_cap_usd": null,
      "daily_fees_usd": 568556,
      "daily_tev_usd": 355867,
      "tev_ratio_used": 0.7,
      "daily_revenue_usd": 355867,
      "tev_source": "defillama_revenue"
    },
    {
      "date": "2023-11-15",
      "price_usd": 1418,
      "market_cap_usd": null,
      "daily_fees_usd": 566470,
      "daily_tev_usd": 355291,
      "tev_ratio_used": 0.7,
      "daily_revenue_usd": 355291,
      "tev_source": "defillama_revenue"
    },
    {
      "date": "2023-11-16",
      "price_usd": 1336,
      "market_cap_usd": null,
      "daily_fees_usd": 569488,
      "daily_tev_usd": 358231,
      "tev_ratio_used": 0.7,
      "daily_revenue_usd": 358231,
      "tev_source": "defillama_revenue"
    },
    {
      "date": "2023-11-17",
      "price_usd": 1362,
      "market_cap_usd": null,
      "daily_fees_usd": 559056,
      "daily_tev_usd": 347494,
      "tev_ratio_used": 0.7,
      "daily_revenue_usd": 347494,
      "tev_source": "defillama_revenue"
    },
    {
      "date": "2023-11-18",
      "price_usd": 1367,
      "market_cap_usd": null,
      "daily_fees_usd": 549657,
      "daily_tev_usd": 334849,
      "tev_ratio_used": 0.7,
      "daily_revenue_usd": 334849,
      "tev_source": "defillama_revenue"
    },
    {
      "date": "2023-11-19",
      "price_usd": 1385,
      "market_cap_usd": null,
      "daily_fees_usd": 538997,
      "daily_tev_usd": 320887,
      "tev_ratio_used": 0.7,
      "daily_revenue_usd": 320887,
      "tev_source": "defillama_revenue"
    },
    {
      "date": "2023-11-20",
      "price_usd": 1403,
      "market_cap_usd": null,
      "daily_fees_usd": 538263,
      "daily_tev_usd": 321493,
      "tev_ratio_used": 0.7,
      "daily_revenue_usd": 321493,
      "tev_source": "defillama_revenue"
    },
    {
      "date": "2023-11-21",
      "price_usd": 1371,
      "market_cap_usd": null,
      "daily_fees_usd": 554514,
      "daily_tev_usd": 336987,
      "tev_ratio_used": 0.7,
      "daily_revenue_usd": 336987,
      "tev_source": "defillama_revenue"
    },
    {
      "date": "2023-11-22",
      "price_usd": 1466,
      "market_cap_usd": null,
      "daily_fees_usd": 554604,
      "daily_tev_usd": 336059,
      "tev_ratio_used": 0.7,
      "daily_revenue_usd": 336059,
      "tev_source": "defillama_revenue"
    },
    {
      "date": "2023-11-23",
      "price_usd": 1471,
      "market_cap_usd": null,
      "daily_fees_usd": 555228,
      "daily_tev_usd": 336430,
      "tev_ratio_used": 0.7,
      "daily_revenue_usd": 336430,
      "tev_source": "defillama_revenue"
    },
    {
      "date": "2023-11-24",
      "price_usd": 1458,
      "market_cap_usd": null,
      "daily_fees_usd": 555981,
      "daily_tev_usd": 336204,
      "tev_ratio_used": 0.7,
      "daily_revenue_usd": 336204,
      "tev_source": "defillama_revenue"
    },
    {
      "date": "2023-11-25",
      "price_usd": 1459,
      "market_cap_usd": null,
      "daily_fees_usd": 557212,
      "daily_tev_usd": 335427,
      "tev_ratio_used": 0.7,
      "daily_revenue_usd": 335427,
      "tev_source": "defillama_revenue"
    },
    {
      "date": "2023-11-26",
      "price_usd": 1486,
      "market_cap_usd": null,
      "daily_fees_usd": 557876,
      "daily_tev_usd": 335694,
      "tev_ratio_used": 0.7,
      "daily_revenue_usd": 335694,
      "tev_source": "defillama_revenue"
    },
    {
      "date": "2023-11-27",
      "price_usd": 1476,
      "market_cap_usd": null,
      "daily_fees_usd": 558478,
      "daily_tev_usd": 337334,
      "tev_ratio_used": 0.7,
      "daily_revenue_usd": 337334,
      "tev_source": "defillama_revenue"
    },
    {
      "date": "2023-11-28",
      "price_usd": 1487,
      "market_cap_usd": null,
      "daily_fees_usd": 559234,
      "daily_tev_usd": 337109,
      "tev_ratio_used": 0.7,
      "daily_revenue_usd": 337109,
      "tev_source": "defillama_revenue"
    },
    {
      "date": "2023-11-29",
      "price_usd": 1523,
      "market_cap_usd": null,
      "daily_fees_usd": 563287,
      "daily_tev_usd": 342079,
      "tev_ratio_used": 0.7,
      "daily_revenue_usd": 342079,
      "tev_source": "defillama_revenue"
    },
    {
      "date": "2023-11-30",
      "price_usd": 1528,
      "market_cap_usd": null,
      "daily_fees_usd": 563939,
      "daily_tev_usd": 342120,
      "tev_ratio_used": 0.7,
      "daily_revenue_usd": 342120,
      "tev_source": "defillama_revenue"
    }
  ]
}