{
  "protocol": "hyperliquid",
  "period": "2024-12",
  "source": "defillama+coingecko",
  "fetched_at": "2026-02-13T21:39:13.068Z",
  "record_count": 9,
  "records": [
    {
      "date": "2024-12-23",
      "price_usd": null,
      "market_cap_usd": null,
      "daily_fees_usd": 1468518,
      "daily_revenue_usd": 1424462,
      "daily_holders_revenue_usd": 1424462,
      "daily_tev_usd": 1424462,
      "tev_source": "defillama_holdersRevenue"
    },
    {
      "date": "2024-12-24",
      "price_usd": null,
      "market_cap_usd": null,
      "daily_fees_usd": 1384305,
      "daily_revenue_usd": 1303665,
      "daily_holders_revenue_usd": 1303665,
      "daily_tev_usd": 1303665,
      "tev_source": "defillama_holdersRevenue"
    },
    {
      "date": "2024-12-25",
      "price_usd": null,
      "market_cap_usd": null,
      "daily_fees_usd": 1077272,
      "daily_revenue_usd": 1014518,
      "daily_holders_revenue_usd": 1014518,
      "daily_tev_usd": 1014518,
      "tev_source": "defillama_holdersRevenue"
    },
    {
      "date": "2024-12-26",
      "price_usd": null,
      "market_cap_usd": null,
      "daily_fees_usd": 1352695,
      "daily_revenue_usd": 1273897,
      "daily_holders_revenue_usd": 1273897,
      "daily_tev_usd": 1273897,
      "tev_source": "defillama_holdersRevenue"
    },
    {
      "date": "2024-12-27",
      "price_usd": null,
      "market_cap_usd": null,
      "daily_fees_usd": 1336367,
      "daily_revenue_usd": 1258520,
      "daily_holders_revenue_usd": 1258520,
      "daily_tev_usd": 1258520,
      "tev_source": "defillama_holdersRevenue"
    },
    {
      "date": "2024-12-28",
      "price_usd": null,
      "market_cap_usd": null,
      "daily_fees_usd": 1008036,
      "daily_revenue_usd": 949315,
      "daily_holders_revenue_usd": 949315,
      "daily_tev_usd": 949315,
      "tev_source": "defillama_holdersRevenue"
    },
    {
      "date": "2024-12-29",
      "price_usd": null,
      "market_cap_usd": null,
      "daily_fees_usd": 500152,
      "daily_revenue_usd": 471167,
      "daily_holders_revenue_usd": 471167,
      "daily_tev_usd": 471167,
      "tev_source": "defillama_holdersRevenue"
    },
    {
      "date": "2024-12-30",
      "price_usd": null,
      "market_cap_usd": null,
      "daily_fees_usd": 1578682,
      "daily_revenue_usd": 1486794,
      "daily_holders_revenue_usd": 1486794,
      "daily_tev_usd": 1486794,
      "tev_source": "defillama_holdersRevenue"
    },
    {
      "date": "2024-12-31",
      "price_usd": null,
      "market_cap_usd": null,
      "daily_fees_usd": 1410195,
      "daily_revenue_usd": 1327977,
      "daily_holders_revenue_usd": 1327977,
      "daily_tev_usd": 1327977,
      "tev_source": "defillama_holdersRevenue"
    }
  ]
}