{
  "protocol": "sky",
  "period": "2020-10",
  "source": "defillama+coingecko",
  "fetched_at": "2026-02-09T07:04:47.985Z",
  "record_count": 31,
  "records": [
    {
      "date": "2020-10-01",
      "price_usd": null,
      "market_cap_usd": null,
      "daily_fees_usd": 30971,
      "daily_tev_usd": 0,
      "tev_ratio_used": 0.7,
      "daily_revenue_usd": 30971,
      "daily_holders_revenue_usd": 0,
      "tev_source": "defillama_holdersRevenue"
    },
    {
      "date": "2020-10-02",
      "price_usd": null,
      "market_cap_usd": null,
      "daily_fees_usd": 30669,
      "daily_tev_usd": 0,
      "tev_ratio_used": 0.7,
      "daily_revenue_usd": 30669,
      "daily_holders_revenue_usd": 0,
      "tev_source": "defillama_holdersRevenue"
    },
    {
      "date": "2020-10-03",
      "price_usd": null,
      "market_cap_usd": null,
      "daily_fees_usd": 30212,
      "daily_tev_usd": 0,
      "tev_ratio_used": 0.7,
      "daily_revenue_usd": 30212,
      "daily_holders_revenue_usd": 0,
      "tev_source": "defillama_holdersRevenue"
    },
    {
      "date": "2020-10-04",
      "price_usd": null,
      "market_cap_usd": null,
      "daily_fees_usd": 26932,
      "daily_tev_usd": 0,
      "tev_ratio_used": 0.7,
      "daily_revenue_usd": 26932,
      "daily_holders_revenue_usd": 0,
      "tev_source": "defillama_holdersRevenue"
    },
    {
      "date": "2020-10-05",
      "price_usd": null,
      "market_cap_usd": null,
      "daily_fees_usd": 26957,
      "daily_tev_usd": 0,
      "tev_ratio_used": 0.7,
      "daily_revenue_usd": 26957,
      "daily_holders_revenue_usd": 0,
      "tev_source": "defillama_holdersRevenue"
    },
    {
      "date": "2020-10-06",
      "price_usd": null,
      "market_cap_usd": null,
      "daily_fees_usd": 27051,
      "daily_tev_usd": 0,
      "tev_ratio_used": 0.7,
      "daily_revenue_usd": 27051,
      "daily_holders_revenue_usd": 0,
      "tev_source": "defillama_holdersRevenue"
    },
    {
      "date": "2020-10-07",
      "price_usd": null,
      "market_cap_usd": null,
      "daily_fees_usd": 26814,
      "daily_tev_usd": 0,
      "tev_ratio_used": 0.7,
      "daily_revenue_usd": 26814,
      "daily_holders_revenue_usd": 0,
      "tev_source": "defillama_holdersRevenue"
    },
    {
      "date": "2020-10-08",
      "price_usd": null,
      "market_cap_usd": null,
      "daily_fees_usd": 27034,
      "daily_tev_usd": 0,
      "tev_ratio_used": 0.7,
      "daily_revenue_usd": 27034,
      "daily_holders_revenue_usd": 0,
      "tev_source": "defillama_holdersRevenue"
    },
    {
      "date": "2020-10-09",
      "price_usd": null,
      "market_cap_usd": null,
      "daily_fees_usd": 26969,
      "daily_tev_usd": 0,
      "tev_ratio_used": 0.7,
      "daily_revenue_usd": 26969,
      "daily_holders_revenue_usd": 0,
      "tev_source": "defillama_holdersRevenue"
    },
    {
      "date": "2020-10-10",
      "price_usd": null,
      "market_cap_usd": null,
      "daily_fees_usd": 26934,
      "daily_tev_usd": 0,
      "tev_ratio_used": 0.7,
      "daily_revenue_usd": 26934,
      "daily_holders_revenue_usd": 0,
      "tev_source": "defillama_holdersRevenue"
    },
    {
      "date": "2020-10-11",
      "price_usd": null,
      "market_cap_usd": null,
      "daily_fees_usd": 26856,
      "daily_tev_usd": 0,
      "tev_ratio_used": 0.7,
      "daily_revenue_usd": 26856,
      "daily_holders_revenue_usd": 0,
      "tev_source": "defillama_holdersRevenue"
    },
    {
      "date": "2020-10-12",
      "price_usd": null,
      "market_cap_usd": null,
      "daily_fees_usd": 26862,
      "daily_tev_usd": 0,
      "tev_ratio_used": 0.7,
      "daily_revenue_usd": 26862,
      "daily_holders_revenue_usd": 0,
      "tev_source": "defillama_holdersRevenue"
    },
    {
      "date": "2020-10-13",
      "price_usd": null,
      "market_cap_usd": null,
      "daily_fees_usd": 27095,
      "daily_tev_usd": 0,
      "tev_ratio_used": 0.7,
      "daily_revenue_usd": 27095,
      "daily_holders_revenue_usd": 0,
      "tev_source": "defillama_holdersRevenue"
    },
    {
      "date": "2020-10-14",
      "price_usd": null,
      "market_cap_usd": null,
      "daily_fees_usd": 26908,
      "daily_tev_usd": 0,
      "tev_ratio_used": 0.7,
      "daily_revenue_usd": 26908,
      "daily_holders_revenue_usd": 0,
      "tev_source": "defillama_holdersRevenue"
    },
    {
      "date": "2020-10-15",
      "price_usd": null,
      "market_cap_usd": null,
      "daily_fees_usd": 26895,
      "daily_tev_usd": 0,
      "tev_ratio_used": 0.7,
      "daily_revenue_usd": 26895,
      "daily_holders_revenue_usd": 0,
      "tev_source": "defillama_holdersRevenue"
    },
    {
      "date": "2020-10-16",
      "price_usd": null,
      "market_cap_usd": null,
      "daily_fees_usd": 26786,
      "daily_tev_usd": 0,
      "tev_ratio_used": 0.7,
      "daily_revenue_usd": 26786,
      "daily_holders_revenue_usd": 0,
      "tev_source": "defillama_holdersRevenue"
    },
    {
      "date": "2020-10-17",
      "price_usd": null,
      "market_cap_usd": null,
      "daily_fees_usd": 26811,
      "daily_tev_usd": 0,
      "tev_ratio_used": 0.7,
      "daily_revenue_usd": 26811,
      "daily_holders_revenue_usd": 0,
      "tev_source": "defillama_holdersRevenue"
    },
    {
      "date": "2020-10-18",
      "price_usd": null,
      "market_cap_usd": null,
      "daily_fees_usd": 26951,
      "daily_tev_usd": 0,
      "tev_ratio_used": 0.7,
      "daily_revenue_usd": 26951,
      "daily_holders_revenue_usd": 0,
      "tev_source": "defillama_holdersRevenue"
    },
    {
      "date": "2020-10-19",
      "price_usd": null,
      "market_cap_usd": null,
      "daily_fees_usd": 27299,
      "daily_tev_usd": 0,
      "tev_ratio_used": 0.7,
      "daily_revenue_usd": 27299,
      "daily_holders_revenue_usd": 0,
      "tev_source": "defillama_holdersRevenue"
    },
    {
      "date": "2020-10-20",
      "price_usd": null,
      "market_cap_usd": null,
      "daily_fees_usd": 27587,
      "daily_tev_usd": 0,
      "tev_ratio_used": 0.7,
      "daily_revenue_usd": 27587,
      "daily_holders_revenue_usd": 0,
      "tev_source": "defillama_holdersRevenue"
    },
    {
      "date": "2020-10-21",
      "price_usd": null,
      "market_cap_usd": null,
      "daily_fees_usd": 28724,
      "daily_tev_usd": 0,
      "tev_ratio_used": 0.7,
      "daily_revenue_usd": 28724,
      "daily_holders_revenue_usd": 0,
      "tev_source": "defillama_holdersRevenue"
    },
    {
      "date": "2020-10-22",
      "price_usd": null,
      "market_cap_usd": null,
      "daily_fees_usd": 28866,
      "daily_tev_usd": 0,
      "tev_ratio_used": 0.7,
      "daily_revenue_usd": 28866,
      "daily_holders_revenue_usd": 0,
      "tev_source": "defillama_holdersRevenue"
    },
    {
      "date": "2020-10-23",
      "price_usd": null,
      "market_cap_usd": null,
      "daily_fees_usd": 30416,
      "daily_tev_usd": 0,
      "tev_ratio_used": 0.7,
      "daily_revenue_usd": 30416,
      "daily_holders_revenue_usd": 0,
      "tev_source": "defillama_holdersRevenue"
    },
    {
      "date": "2020-10-24",
      "price_usd": null,
      "market_cap_usd": null,
      "daily_fees_usd": 30491,
      "daily_tev_usd": 0,
      "tev_ratio_used": 0.7,
      "daily_revenue_usd": 30491,
      "daily_holders_revenue_usd": 0,
      "tev_source": "defillama_holdersRevenue"
    },
    {
      "date": "2020-10-25",
      "price_usd": null,
      "market_cap_usd": null,
      "daily_fees_usd": 30580,
      "daily_tev_usd": 0,
      "tev_ratio_used": 0.7,
      "daily_revenue_usd": 30580,
      "daily_holders_revenue_usd": 0,
      "tev_source": "defillama_holdersRevenue"
    },
    {
      "date": "2020-10-26",
      "price_usd": null,
      "market_cap_usd": null,
      "daily_fees_usd": 30755,
      "daily_tev_usd": 0,
      "tev_ratio_used": 0.7,
      "daily_revenue_usd": 30755,
      "daily_holders_revenue_usd": 0,
      "tev_source": "defillama_holdersRevenue"
    },
    {
      "date": "2020-10-27",
      "price_usd": null,
      "market_cap_usd": null,
      "daily_fees_usd": 30847,
      "daily_tev_usd": 0,
      "tev_ratio_used": 0.7,
      "daily_revenue_usd": 30847,
      "daily_holders_revenue_usd": 0,
      "tev_source": "defillama_holdersRevenue"
    },
    {
      "date": "2020-10-28",
      "price_usd": null,
      "market_cap_usd": null,
      "daily_fees_usd": 30996,
      "daily_tev_usd": 0,
      "tev_ratio_used": 0.7,
      "daily_revenue_usd": 30996,
      "daily_holders_revenue_usd": 0,
      "tev_source": "defillama_holdersRevenue"
    },
    {
      "date": "2020-10-29",
      "price_usd": null,
      "market_cap_usd": null,
      "daily_fees_usd": 31178,
      "daily_tev_usd": 0,
      "tev_ratio_used": 0.7,
      "daily_revenue_usd": 31178,
      "daily_holders_revenue_usd": 0,
      "tev_source": "defillama_holdersRevenue"
    },
    {
      "date": "2020-10-30",
      "price_usd": null,
      "market_cap_usd": null,
      "daily_fees_usd": 30696,
      "daily_tev_usd": 0,
      "tev_ratio_used": 0.7,
      "daily_revenue_usd": 30696,
      "daily_holders_revenue_usd": 0,
      "tev_source": "defillama_holdersRevenue"
    },
    {
      "date": "2020-10-31",
      "price_usd": null,
      "market_cap_usd": null,
      "daily_fees_usd": 30773,
      "daily_tev_usd": 0,
      "tev_ratio_used": 0.7,
      "daily_revenue_usd": 30773,
      "daily_holders_revenue_usd": 0,
      "tev_source": "defillama_holdersRevenue"
    }
  ]
}