{
  "updated_at": "2026-02-26",
  "source": "CoinGecko API",
  "initial_supply": 1000000000,
  "total_supply": 898594420.0366304,
  "circulating_supply": 633629603.6037512,
  "total_burned": 101405579.96336961,
  "burn_percentage": 10.1406,
  "current_price": 4.02,
  "burned_value_usd": 407650431.45,
  "target_supply": null,
  "monthly_burns": [
    {
      "month": "2026-02",
      "date": "2026-02-26",
      "amount": 101405579.96336961,
      "value_usd": 407650431.45
    }
  ],
  "note": "UNI 通过 buyback 机制销毁"
}