{
  "protocol": "ethena",
  "updated_at": "2026-02-24T18:42:51.739147+00:00",
  "data_sources": {
    "tvl": "DefiLlama",
    "fees": "DefiLlama",
    "market": "CoinGecko"
  },
  "latest_record": {
    "date": "2026-02-24",
    "price_usd": 0.098706,
    "market_cap_usd": 811797552,
    "fdv_usd": 1480481857,
    "circulating_supply": 8225000000.0,
    "total_supply": 15000000000.0,
    "tvl_usd": 6082561700.308856,
    "daily_fees_usd": 718,
    "daily_tev_usd": 0,
    "tev_ratio_used": 0
  },
  "metrics": {
    "trailing_30d_fees_usd": 19795062,
    "trailing_30d_tev_usd": 0,
    "annualized_fees_usd": 237540744,
    "annualized_tev_usd": 0,
    "current_market_cap_usd": 811797552,
    "tev_yield": "0.00%",
    "tev_yield_decimal": 0.0,
    "tvl_usd": 6082561700.308856,
    "mcap_tvl_ratio": 0.1335,
    "calculated_at": "2026-02-24T18:42:51.739147+00:00"
  },
  "fees_breakdown": {
    "ethena-usde": 19795062
  }
}